LinearModel/__init__.py
LinearModel/regression.py
LinearModel-1.0.1.dist-info/LICENCE.txt
LinearModel-1.0.1.dist-info/METADATA
LinearModel-1.0.1.dist-info/WHEEL
LinearModel-1.0.1.dist-info/top_level.txt
LinearModel-1.0.1.dist-info/RECORD
